python_eloqua_wrapper/__init__.py
python_eloqua_wrapper/cdo_info.py
python_eloqua_wrapper/cdo_record.py
python_eloqua_wrapper/contact_record.py
python_eloqua_wrapper/eloqua_session.py
python_eloqua_wrapper-0.0.9.dist-info/METADATA
python_eloqua_wrapper-0.0.9.dist-info/WHEEL
python_eloqua_wrapper-0.0.9.dist-info/top_level.txt
python_eloqua_wrapper-0.0.9.dist-info/RECORD
