Metadata-Version: 2.1
Name: python-eloqua-wrapper
Version: 0.0.9
Summary: A wrapper for Eloqua's HTTP REST API
Home-page: https://gitlab.corp.redhat.com/mkt-ops-de/python-eloqua-wrapper.git
Author: Tim Sawicki
Author-email: tsawicki@redhat.com
License: UNKNOWN
Platform: UNKNOWN
Classifier: Programming Language :: Python :: 3
Classifier: License :: OSI Approved :: MIT License
Classifier: Operating System :: OS Independent
Requires-Dist: pytz
Requires-Dist: requests
